LICENSE.txt
MANIFEST.in
README.rst
setup.py
django_fs_smsc.egg-info/PKG-INFO
django_fs_smsc.egg-info/SOURCES.txt
django_fs_smsc.egg-info/dependency_links.txt
django_fs_smsc.egg-info/requires.txt
django_fs_smsc.egg-info/top_level.txt
smsc/__init__.py
smsc/admin.py
smsc/api.py
smsc/constants.py
smsc/exceptions.py
smsc/models.py
smsc/settings.py
smsc/urls.py
smsc/views.py
smsc/locale/ru/LC_MESSAGES/django.mo
smsc/locale/ru/LC_MESSAGES/django.po
smsc/migrations/0001_initial.py
smsc/migrations/0002_auto__add_message.py
smsc/migrations/__init__.py