Metadata-Version: 1.1
Name: django-fs-smsc
Version: 0.1
Summary: Django integration with SMS Centre
Home-page: https://bitbucket.org/fogstream/django-fs-smsc
Author: Yuri Lya
Author-email: yuri.lya@fogstream.ru
License: The MIT License (MIT)
Platform: UNKNOWN
Classifier: Development Status :: 5 - Production/Stable
Classifier: Environment :: Web Environment
Classifier: Intended Audience :: Developers
Classifier: Operating System :: OS Independent
Classifier: Programming Language :: Python
Classifier: Framework :: Django
